aioeeveemobility/__init__.py
aioeeveemobility/client.py
aioeeveemobility/const.py
aioeeveemobility-0.1.3.dist-info/LICENSE
aioeeveemobility-0.1.3.dist-info/METADATA
aioeeveemobility-0.1.3.dist-info/WHEEL
aioeeveemobility-0.1.3.dist-info/top_level.txt
aioeeveemobility-0.1.3.dist-info/RECORD
