Metadata-Version: 2.1
Name: aioeeveemobility
Version: 0.1.3
Summary: Module to communicate to the EEVEE Mobility API
Home-page: https://github.com/geertmeersman/aioeeveemobility
Author: Geert Meersman
Author-email: geertmeersman@gmail.com
License: MIT
Classifier: Programming Language :: Python :: 3
Classifier: License :: OSI Approved :: Apache Software License
Classifier: Operating System :: OS Independent
License-File: LICENSE
Requires-Dist: aiohttp
Requires-Dist: pip <24.1,>=8.0.3
Requires-Dist: ruff ==0.3.3
